data/__init__.py
data/f2404_fs16.896_one_hop.iq
pyhacores/__init__.py
pyhacores/cordic/__init__.py
pyhacores/cordic/cordic_core.py
pyhacores/cordic/nco.py
pyhacores/cordic/to_polar.py
pyhacores/filter/__init__.py
pyhacores/filter/dc_removal.py
pyhacores/filter/fir.py
pyhacores/filter/moving_average.py
pyhacores/packet/__init__.py
pyhacores/packet/crc16.py
pyhacores/packet/header_correlator.py
pyhacores/radio/__init__.py
pyhacores/radio/quadrature_demodulator.py
pyhacores/util/__init__.py
pyhacores/util/blade_rf.py
pyhacores/util/complex.py
pyhacores-0.1.0.dist-info/DESCRIPTION.rst
pyhacores-0.1.0.dist-info/METADATA
pyhacores-0.1.0.dist-info/RECORD
pyhacores-0.1.0.dist-info/WHEEL
pyhacores-0.1.0.dist-info/metadata.json
pyhacores-0.1.0.dist-info/top_level.txt
under_construction/__init__.py
under_construction/clock_recovery/__init__.py
under_construction/clock_recovery/doubler.py
under_construction/clock_recovery/gardner.py
under_construction/clock_recovery/test_.py
under_construction/clock_recovery/simple_gardner/__init__.py
under_construction/clock_recovery/simple_gardner/gardner.py
under_construction/clock_recovery/simple_gardner/test_.py
under_construction/experiments/__init__.py
under_construction/experiments/cdt.py
under_construction/experiments/experiment.py
under_construction/experiments/speed.py
under_construction/filter/__init__.py
under_construction/filter/phase_shifting_fir/__init__.py
under_construction/filter/phase_shifting_fir/model.py
under_construction/filter/phase_shifting_fir/test_.py
under_construction/fir_alt/__init__.py
under_construction/fir_alt/model_atom.py
under_construction/fir_alt/test_atom.py
under_construction/fsk_demodulator/__init__.py
under_construction/fsk_demodulator/model.py
under_construction/fsk_demodulator/test_.py
under_construction/fsk_modulator/__init__.py
under_construction/fsk_modulator/model.py
under_construction/fsk_modulator/test_.py
