Metadata-Version: 2.0
Name: pyhacores
Version: 0.1.0
Summary: Cores written in Pyha
Home-page: https://github.com/gasparka/pyhacores
Author: Gaspar Karm
Author-email: gkarm@live.com
License: Apache Software License 2.0
Platform: UNKNOWN
Classifier: Development Status :: 3 - Alpha
Classifier: Intended Audience :: Developers
Classifier: Topic :: Software Development :: Build Tools
Classifier: License :: OSI Approved :: Apache Software License
Classifier: Programming Language :: Python :: 3.6
Requires-Dist: pyha (==0.0.5.post2)
Requires-Dist: numpy (==1.13.3)
Requires-Dist: scipy (==1.0.0)
Requires-Dist: pytest (==3.3.1)
